[
    {
        "key": "AFG_Afghanistan_3",
        "name": "Afghanistan"
    },
    {
        "key": "XAD_Akrotiri and Dhekelia_2",
        "name": "Akrotiri and Dhekelia"
    },
    {
        "key": "ALA_Åland_2",
        "name": "Åland"
    },
    {
        "key": "ALB_Albania_4",
        "name": "Albania"
    },
    {
        "key": "DZA_Algeria_3",
        "name": "Algeria"
    },
    {
        "key": "ASM_American Samoa_4",
        "name": "American Samoa"
    },
    {
        "key": "AND_Andorra_2",
        "name": "Andorra"
    },
    {
        "key": "AGO_Angola_4",
        "name": "Angola"
    },
    {
        "key": "AIA_Anguilla_1",
        "name": "Anguilla"
    },
    {
        "key": "ATA_Antarctica_1",
        "name": "Antarctica"
    },
    {
        "key": "ATG_Antigua and Barbuda_2",
        "name": "Antigua and Barbuda"
    },
    {
        "key": "ARG_Argentina_3",
        "name": "Argentina"
    },
    {
        "key": "ARM_Armenia_2",
        "name": "Armenia"
    },
    {
        "key": "ABW_Aruba_1",
        "name": "Aruba"
    },
    {
        "key": "AUS_Australia_3",
        "name": "Australia"
    },
    {
        "key": "AUT_Austria_4",
        "name": "Austria"
    },
    {
        "key": "AZE_Azerbaijan_3",
        "name": "Azerbaijan"
    },
    {
        "key": "BHS_Bahamas_2",
        "name": "Bahamas"
    },
    {
        "key": "BHR_Bahrain_2",
        "name": "Bahrain"
    },
    {
        "key": "BGD_Bangladesh_4",
        "name": "Bangladesh"
    },
    {
        "key": "BRB_Barbados_2",
        "name": "Barbados"
    },
    {
        "key": "BLR_Belarus_3",
        "name": "Belarus"
    },
    {
        "key": "BEL_Belgium_5",
        "name": "Belgium"
    },
    {
        "key": "BLZ_Belize_2",
        "name": "Belize"
    },
    {
        "key": "BEN_Benin_3",
        "name": "Benin"
    },
    {
        "key": "BMU_Bermuda_2",
        "name": "Bermuda"
    },
    {
        "key": "BTN_Bhutan_3",
        "name": "Bhutan"
    },
    {
        "key": "BOL_Bolivia_4",
        "name": "Bolivia"
    },
    {
        "key": "BES_Bonaire, Saint Eustatius and Saba_2",
        "name": "Bonaire, Saint Eustatius and Saba"
    },
    {
        "key": "BIH_Bosnia and Herzegovina_4",
        "name": "Bosnia and Herzegovina"
    },
    {
        "key": "BWA_Botswana_3",
        "name": "Botswana"
    },
    {
        "key": "BVT_Bouvet Island_1",
        "name": "Bouvet Island"
    },
    {
        "key": "BRA_Brazil_4",
        "name": "Brazil"
    },
    {
        "key": "IOT_British Indian Ocean Territory_1",
        "name": "British Indian Ocean Territory"
    },
    {
        "key": "VGB_British Virgin Islands_2",
        "name": "British Virgin Islands"
    },
    {
        "key": "BRN_Brunei_3",
        "name": "Brunei"
    },
    {
        "key": "BGR_Bulgaria_3",
        "name": "Bulgaria"
    },
    {
        "key": "BFA_Burkina Faso_4",
        "name": "Burkina Faso"
    },
    {
        "key": "BDI_Burundi_5",
        "name": "Burundi"
    },
    {
        "key": "KHM_Cambodia_5",
        "name": "Cambodia"
    },
    {
        "key": "CMR_Cameroon_4",
        "name": "Cameroon"
    },
    {
        "key": "CAN_Canada_4",
        "name": "Canada"
    },
    {
        "key": "CPV_Cape Verde_2",
        "name": "Cape Verde"
    },
    {
        "key": "XCA_Caspian Sea_1",
        "name": "Caspian Sea"
    },
    {
        "key": "CYM_Cayman Islands_2",
        "name": "Cayman Islands"
    },
    {
        "key": "CAF_Central African Republic_3",
        "name": "Central African Republic"
    },
    {
        "key": "TCD_Chad_4",
        "name": "Chad"
    },
    {
        "key": "CHL_Chile_4",
        "name": "Chile"
    },
    {
        "key": "CHN_China_4",
        "name": "China"
    },
    {
        "key": "CXR_Christmas Island_1",
        "name": "Christmas Island"
    },
    {
        "key": "XCL_Clipperton Island_1",
        "name": "Clipperton Island"
    },
    {
        "key": "CCK_Cocos Islands_1",
        "name": "Cocos Islands"
    },
    {
        "key": "COL_Colombia_3",
        "name": "Colombia"
    },
    {
        "key": "COM_Comoros_2",
        "name": "Comoros"
    },
    {
        "key": "COK_Cook Islands_1",
        "name": "Cook Islands"
    },
    {
        "key": "CRI_Costa Rica_3",
        "name": "Costa Rica"
    },
    {
        "key": "CIV_Côte d'Ivoire_5",
        "name": "Côte d'Ivoire"
    },
    {
        "key": "HRV_Croatia_3",
        "name": "Croatia"
    },
    {
        "key": "CUB_Cuba_3",
        "name": "Cuba"
    },
    {
        "key": "CUW_Curaçao_1",
        "name": "Curaçao"
    },
    {
        "key": "CYP_Cyprus_2",
        "name": "Cyprus"
    },
    {
        "key": "CZE_Czech Republic_3",
        "name": "Czech Republic"
    },
    {
        "key": "COD_Democratic Republic of the Congo_4",
        "name": "Democratic Republic of the Congo"
    },
    {
        "key": "DNK_Denmark_3",
        "name": "Denmark"
    },
    {
        "key": "DJI_Djibouti_3",
        "name": "Djibouti"
    },
    {
        "key": "DMA_Dominica_2",
        "name": "Dominica"
    },
    {
        "key": "DOM_Dominican Republic_3",
        "name": "Dominican Republic"
    },
    {
        "key": "ECU_Ecuador_4",
        "name": "Ecuador"
    },
    {
        "key": "EGY_Egypt_3",
        "name": "Egypt"
    },
    {
        "key": "SLV_El Salvador_3",
        "name": "El Salvador"
    },
    {
        "key": "GNQ_Equatorial Guinea_3",
        "name": "Equatorial Guinea"
    },
    {
        "key": "ERI_Eritrea_3",
        "name": "Eritrea"
    },
    {
        "key": "EST_Estonia_4",
        "name": "Estonia"
    },
    {
        "key": "ETH_Ethiopia_4",
        "name": "Ethiopia"
    },
    {
        "key": "FLK_Falkland Islands_1",
        "name": "Falkland Islands"
    },
    {
        "key": "FRO_Faroe Islands_3",
        "name": "Faroe Islands"
    },
    {
        "key": "FJI_Fiji_3",
        "name": "Fiji"
    },
    {
        "key": "FIN_Finland_5",
        "name": "Finland"
    },
    {
        "key": "FRA_France_6",
        "name": "France"
    },
    {
        "key": "GUF_French Guiana_3",
        "name": "French Guiana"
    },
    {
        "key": "PYF_French Polynesia_2",
        "name": "French Polynesia"
    },
    {
        "key": "ATF_French Southern Territories_2",
        "name": "French Southern Territories"
    },
    {
        "key": "GAB_Gabon_3",
        "name": "Gabon"
    },
    {
        "key": "GMB_Gambia_3",
        "name": "Gambia"
    },
    {
        "key": "GEO_Georgia_3",
        "name": "Georgia"
    },
    {
        "key": "DEU_Germany_5",
        "name": "Germany"
    },
    {
        "key": "GHA_Ghana_3",
        "name": "Ghana"
    },
    {
        "key": "GIB_Gibraltar_1",
        "name": "Gibraltar"
    },
    {
        "key": "GRC_Greece_4",
        "name": "Greece"
    },
    {
        "key": "GRL_Greenland_2",
        "name": "Greenland"
    },
    {
        "key": "GRD_Grenada_2",
        "name": "Grenada"
    },
    {
        "key": "GLP_Guadeloupe_3",
        "name": "Guadeloupe"
    },
    {
        "key": "GUM_Guam_2",
        "name": "Guam"
    },
    {
        "key": "GTM_Guatemala_3",
        "name": "Guatemala"
    },
    {
        "key": "GGY_Guernsey_2",
        "name": "Guernsey"
    },
    {
        "key": "GIN_Guinea_4",
        "name": "Guinea"
    },
    {
        "key": "GNB_Guinea-Bissau_3",
        "name": "Guinea-Bissau"
    },
    {
        "key": "GUY_Guyana_3",
        "name": "Guyana"
    },
    {
        "key": "HTI_Haiti_5",
        "name": "Haiti"
    },
    {
        "key": "HMD_Heard Island and McDonald Islands_1",
        "name": "Heard Island and McDonald Islands"
    },
    {
        "key": "HND_Honduras_3",
        "name": "Honduras"
    },
    {
        "key": "HKG_Hong Kong_2",
        "name": "Hong Kong"
    },
    {
        "key": "HUN_Hungary_3",
        "name": "Hungary"
    },
    {
        "key": "ISL_Iceland_3",
        "name": "Iceland"
    },
    {
        "key": "IND_India_4",
        "name": "India"
    },
    {
        "key": "IDN_Indonesia_3",
        "name": "Indonesia"
    },
    {
        "key": "IRN_Iran_3",
        "name": "Iran"
    },
    {
        "key": "IRQ_Iraq_3",
        "name": "Iraq"
    },
    {
        "key": "IRL_Ireland_2",
        "name": "Ireland"
    },
    {
        "key": "IMN_Isle of Man_3",
        "name": "Isle of Man"
    },
    {
        "key": "ISR_Israel_2",
        "name": "Israel"
    },
    {
        "key": "ITA_Italy_4",
        "name": "Italy"
    },
    {
        "key": "JAM_Jamaica_2",
        "name": "Jamaica"
    },
    {
        "key": "JPN_Japan_3",
        "name": "Japan"
    },
    {
        "key": "JEY_Jersey_2",
        "name": "Jersey"
    },
    {
        "key": "JOR_Jordan_3",
        "name": "Jordan"
    },
    {
        "key": "KAZ_Kazakhstan_3",
        "name": "Kazakhstan"
    },
    {
        "key": "KEN_Kenya_4",
        "name": "Kenya"
    },
    {
        "key": "KIR_Kiribati_1",
        "name": "Kiribati"
    },
    {
        "key": "XKO_Kosovo_3",
        "name": "Kosovo"
    },
    {
        "key": "KWT_Kuwait_2",
        "name": "Kuwait"
    },
    {
        "key": "KGZ_Kyrgyzstan_3",
        "name": "Kyrgyzstan"
    },
    {
        "key": "LAO_Laos_3",
        "name": "Laos"
    },
    {
        "key": "LVA_Latvia_3",
        "name": "Latvia"
    },
    {
        "key": "LBN_Lebanon_4",
        "name": "Lebanon"
    },
    {
        "key": "LSO_Lesotho_2",
        "name": "Lesotho"
    },
    {
        "key": "LBR_Liberia_4",
        "name": "Liberia"
    },
    {
        "key": "LBY_Libya_2",
        "name": "Libya"
    },
    {
        "key": "LIE_Liechtenstein_2",
        "name": "Liechtenstein"
    },
    {
        "key": "LTU_Lithuania_3",
        "name": "Lithuania"
    },
    {
        "key": "LUX_Luxembourg_5",
        "name": "Luxembourg"
    },
    {
        "key": "MAC_Macao_3",
        "name": "Macao"
    },
    {
        "key": "MKD_Macedonia_2",
        "name": "Macedonia"
    },
    {
        "key": "MDG_Madagascar_5",
        "name": "Madagascar"
    },
    {
        "key": "MWI_Malawi_4",
        "name": "Malawi"
    },
    {
        "key": "MYS_Malaysia_3",
        "name": "Malaysia"
    },
    {
        "key": "MDV_Maldives_1",
        "name": "Maldives"
    },
    {
        "key": "MLI_Mali_5",
        "name": "Mali"
    },
    {
        "key": "MLT_Malta_1",
        "name": "Malta"
    },
    {
        "key": "MHL_Marshall Islands_1",
        "name": "Marshall Islands"
    },
    {
        "key": "MTQ_Martinique_3",
        "name": "Martinique"
    },
    {
        "key": "MRT_Mauritania_3",
        "name": "Mauritania"
    },
    {
        "key": "MUS_Mauritius_2",
        "name": "Mauritius"
    },
    {
        "key": "MYT_Mayotte_2",
        "name": "Mayotte"
    },
    {
        "key": "MEX_Mexico_3",
        "name": "Mexico"
    },
    {
        "key": "FSM_Micronesia_2",
        "name": "Micronesia"
    },
    {
        "key": "MDA_Moldova_2",
        "name": "Moldova"
    },
    {
        "key": "MCO_Monaco_1",
        "name": "Monaco"
    },
    {
        "key": "MNG_Mongolia_3",
        "name": "Mongolia"
    },
    {
        "key": "MNE_Montenegro_2",
        "name": "Montenegro"
    },
    {
        "key": "MSR_Montserrat_2",
        "name": "Montserrat"
    },
    {
        "key": "MAR_Morocco_5",
        "name": "Morocco"
    },
    {
        "key": "MOZ_Mozambique_4",
        "name": "Mozambique"
    },
    {
        "key": "MMR_Myanmar_4",
        "name": "Myanmar"
    },
    {
        "key": "NAM_Namibia_3",
        "name": "Namibia"
    },
    {
        "key": "NRU_Nauru_2",
        "name": "Nauru"
    },
    {
        "key": "NPL_Nepal_5",
        "name": "Nepal"
    },
    {
        "key": "NLD_Netherlands_3",
        "name": "Netherlands"
    },
    {
        "key": "NCL_New Caledonia_3",
        "name": "New Caledonia"
    },
    {
        "key": "NZL_New Zealand_4",
        "name": "New Zealand"
    },
    {
        "key": "NIC_Nicaragua_3",
        "name": "Nicaragua"
    },
    {
        "key": "NER_Niger_4",
        "name": "Niger"
    },
    {
        "key": "NGA_Nigeria_3",
        "name": "Nigeria"
    },
    {
        "key": "NIU_Niue_1",
        "name": "Niue"
    },
    {
        "key": "NFK_Norfolk Island_1",
        "name": "Norfolk Island"
    },
    {
        "key": "PRK_North Korea_3",
        "name": "North Korea"
    },
    {
        "key": "XNC_Northern Cyprus_2",
        "name": "Northern Cyprus"
    },
    {
        "key": "MNP_Northern Mariana Islands_2",
        "name": "Northern Mariana Islands"
    },
    {
        "key": "NOR_Norway_3",
        "name": "Norway"
    },
    {
        "key": "OMN_Oman_3",
        "name": "Oman"
    },
    {
        "key": "PAK_Pakistan_4",
        "name": "Pakistan"
    },
    {
        "key": "PLW_Palau_2",
        "name": "Palau"
    },
    {
        "key": "PSE_Palestina_3",
        "name": "Palestina"
    },
    {
        "key": "PAN_Panama_4",
        "name": "Panama"
    },
    {
        "key": "PNG_Papua New Guinea_3",
        "name": "Papua New Guinea"
    },
    {
        "key": "PRY_Paraguay_3",
        "name": "Paraguay"
    },
    {
        "key": "PER_Peru_4",
        "name": "Peru"
    },
    {
        "key": "PHL_Philippines_4",
        "name": "Philippines"
    },
    {
        "key": "PCN_Pitcairn Islands_1",
        "name": "Pitcairn Islands"
    },
    {
        "key": "POL_Poland_3",
        "name": "Poland"
    },
    {
        "key": "PRT_Portugal_4",
        "name": "Portugal"
    },
    {
        "key": "PRI_Puerto Rico_2",
        "name": "Puerto Rico"
    },
    {
        "key": "QAT_Qatar_2",
        "name": "Qatar"
    },
    {
        "key": "COG_Republic of Congo_3",
        "name": "Republic of Congo"
    },
    {
        "key": "REU_Reunion_3",
        "name": "Reunion"
    },
    {
        "key": "ROU_Romania_3",
        "name": "Romania"
    },
    {
        "key": "RUS_Russia_4",
        "name": "Russia"
    },
    {
        "key": "RWA_Rwanda_6",
        "name": "Rwanda"
    },
    {
        "key": "BLM_Saint-Barthélemy_1",
        "name": "Saint-Barthélemy"
    },
    {
        "key": "MAF_Saint-Martin_1",
        "name": "Saint-Martin"
    },
    {
        "key": "SHN_Saint Helena_3",
        "name": "Saint Helena"
    },
    {
        "key": "KNA_Saint Kitts and Nevis_2",
        "name": "Saint Kitts and Nevis"
    },
    {
        "key": "LCA_Saint Lucia_2",
        "name": "Saint Lucia"
    },
    {
        "key": "SPM_Saint Pierre and Miquelon_2",
        "name": "Saint Pierre and Miquelon"
    },
    {
        "key": "VCT_Saint Vincent and the Grenadines_2",
        "name": "Saint Vincent and the Grenadines"
    },
    {
        "key": "WSM_Samoa_3",
        "name": "Samoa"
    },
    {
        "key": "SMR_San Marino_2",
        "name": "San Marino"
    },
    {
        "key": "STP_Sao Tome and Principe_3",
        "name": "Sao Tome and Principe"
    },
    {
        "key": "SAU_Saudi Arabia_2",
        "name": "Saudi Arabia"
    },
    {
        "key": "SEN_Senegal_5",
        "name": "Senegal"
    },
    {
        "key": "SRB_Serbia_3",
        "name": "Serbia"
    },
    {
        "key": "SYC_Seychelles_2",
        "name": "Seychelles"
    },
    {
        "key": "SLE_Sierra Leone_4",
        "name": "Sierra Leone"
    },
    {
        "key": "SGP_Singapore_2",
        "name": "Singapore"
    },
    {
        "key": "SXM_Sint Maarten_1",
        "name": "Sint Maarten"
    },
    {
        "key": "SVK_Slovakia_3",
        "name": "Slovakia"
    },
    {
        "key": "SVN_Slovenia_3",
        "name": "Slovenia"
    },
    {
        "key": "SLB_Solomon Islands_3",
        "name": "Solomon Islands"
    },
    {
        "key": "SOM_Somalia_3",
        "name": "Somalia"
    },
    {
        "key": "ZAF_South Africa_5",
        "name": "South Africa"
    },
    {
        "key": "SGS_South Georgia and the South Sandwich Islands_1",
        "name": "South Georgia and the South Sandwich Islands"
    },
    {
        "key": "KOR_South Korea_3",
        "name": "South Korea"
    },
    {
        "key": "SSD_South Sudan_4",
        "name": "South Sudan"
    },
    {
        "key": "ESP_Spain_5",
        "name": "Spain"
    },
    {
        "key": "LKA_Sri Lanka_3",
        "name": "Sri Lanka"
    },
    {
        "key": "SDN_Sudan_4",
        "name": "Sudan"
    },
    {
        "key": "SUR_Suriname_3",
        "name": "Suriname"
    },
    {
        "key": "SJM_Svalbard and Jan Mayen_2",
        "name": "Svalbard and Jan Mayen"
    },
    {
        "key": "SWZ_Swaziland_3",
        "name": "Swaziland"
    },
    {
        "key": "SWE_Sweden_3",
        "name": "Sweden"
    },
    {
        "key": "CHE_Switzerland_4",
        "name": "Switzerland"
    },
    {
        "key": "SYR_Syria_3",
        "name": "Syria"
    },
    {
        "key": "TWN_Taiwan_3",
        "name": "Taiwan"
    },
    {
        "key": "TJK_Tajikistan_4",
        "name": "Tajikistan"
    },
    {
        "key": "TZA_Tanzania_4",
        "name": "Tanzania"
    },
    {
        "key": "THA_Thailand_4",
        "name": "Thailand"
    },
    {
        "key": "TLS_Timor-Leste_4",
        "name": "Timor-Leste"
    },
    {
        "key": "TGO_Togo_3",
        "name": "Togo"
    },
    {
        "key": "TKL_Tokelau_2",
        "name": "Tokelau"
    },
    {
        "key": "TON_Tonga_2",
        "name": "Tonga"
    },
    {
        "key": "TTO_Trinidad and Tobago_2",
        "name": "Trinidad and Tobago"
    },
    {
        "key": "TUN_Tunisia_3",
        "name": "Tunisia"
    },
    {
        "key": "TUR_Turkey_3",
        "name": "Turkey"
    },
    {
        "key": "TKM_Turkmenistan_2",
        "name": "Turkmenistan"
    },
    {
        "key": "TCA_Turks and Caicos Islands_2",
        "name": "Turks and Caicos Islands"
    },
    {
        "key": "TUV_Tuvalu_2",
        "name": "Tuvalu"
    },
    {
        "key": "UGA_Uganda_5",
        "name": "Uganda"
    },
    {
        "key": "UKR_Ukraine_3",
        "name": "Ukraine"
    },
    {
        "key": "ARE_United Arab Emirates_2",
        "name": "United Arab Emirates"
    },
    {
        "key": "GBR_United Kingdom_3",
        "name": "United Kingdom"
    },
    {
        "key": "USA_United States_3",
        "name": "United States"
    },
    {
        "key": "UMI_United States Minor Outlying Islands_2",
        "name": "United States Minor Outlying Islands"
    },
    {
        "key": "URY_Uruguay_3",
        "name": "Uruguay"
    },
    {
        "key": "UZB_Uzbekistan_3",
        "name": "Uzbekistan"
    },
    {
        "key": "VUT_Vanuatu_3",
        "name": "Vanuatu"
    },
    {
        "key": "VAT_Vatican City_1",
        "name": "Vatican City"
    },
    {
        "key": "VEN_Venezuela_3",
        "name": "Venezuela"
    },
    {
        "key": "VNM_Vietnam_4",
        "name": "Vietnam"
    },
    {
        "key": "VIR_Virgin Islands, U.S._3",
        "name": "Virgin Islands, U.S."
    },
    {
        "key": "WLF_Wallis and Futuna_3",
        "name": "Wallis and Futuna"
    },
    {
        "key": "ESH_Western Sahara_2",
        "name": "Western Sahara"
    },
    {
        "key": "YEM_Yemen_3",
        "name": "Yemen"
    },
    {
        "key": "ZMB_Zambia_3",
        "name": "Zambia"
    },
    {
        "key": "ZWE_Zimbabwe_3",
        "name": "Zimbabwe"
    }
]